multidict/__init__.py
multidict/_abc.py
multidict/_compat.py
multidict/_multidict_py.py
multidict/py.typed
multidict-6.6.2.dist-info/licenses/LICENSE
multidict-6.6.2.dist-info/METADATA
multidict-6.6.2.dist-info/WHEEL
multidict-6.6.2.dist-info/top_level.txt
multidict-6.6.2.dist-info/RECORD
