Metadata-Version: 2.4
Name: multidict
Version: 6.6.2
Summary: multidict implementation
Home-page: https://github.com/aio-libs/multidict
Author: Andrew Svetlov
Author-email: andrew.svetlov@gmail.com
License: Apache License 2.0
Project-URL: Chat: Matrix, https://matrix.to/#/#aio-libs:matrix.org
Project-URL: Chat: Matrix Space, https://matrix.to/#/#aio-libs-space:matrix.org
Project-URL: CI: GitHub, https://github.com/aio-libs/multidict/actions
Project-URL: Code of Conduct, https://github.com/aio-libs/.github/blob/master/CODE_OF_CONDUCT.md
Project-URL: Coverage: codecov, https://codecov.io/github/aio-libs/multidict
Project-URL: Docs: Changelog, https://multidict.aio-libs.org/en/latest/changes/
Project-URL: Docs: RTD, https://multidict.aio-libs.org
Project-URL: GitHub: issues, https://github.com/aio-libs/multidict/issues
Project-URL: GitHub: repo, https://github.com/aio-libs/multidict
Classifier: Development Status :: 5 - Production/Stable
Classifier: Intended Audience :: Developers
Classifier: Programming Language :: Python
Classifier: Programming Language :: Python :: 3
Classifier: Programming Language :: Python :: 3.9
Classifier: Programming Language :: Python :: 3.10
Classifier: Programming Language :: Python :: 3.11
Classifier: Programming Language :: Python :: 3.12
Classifier: Programming Language :: Python :: 3.13
Requires-Python: >=3.9
License-File: LICENSE
Requires-Dist: typing-extensions>=4.1.0; python_version < "3.11"
Dynamic: license-file
